LICENSE.txt
MANIFEST.in
README.rst
setup.py
pyTerra/__init__.py
pyTerra/api.py
pyTerra/image.py
pyTerra.egg-info/PKG-INFO
pyTerra.egg-info/SOURCES.txt
pyTerra.egg-info/dependency_links.txt
pyTerra.egg-info/requires.txt
pyTerra.egg-info/top_level.txt
tests/__init__.py
tests/__init__.pyc
tests/api.py
tests/api.pyc
tests/image.py
tests/image.pyc