Metadata-Version: 1.0
Name: pyTerra
Version: 0.9
Summary: Terraserver Module for Python
Home-page: http://github.com/hobu/pyterra/
Author: Howard Butler
Author-email: hobu.inc@gmail.com
License: UNKNOWN
Platform: UNKNOWN
Classifier: Development Status :: 4 - Beta
Classifier: Intended Audience :: Developers
Classifier: Intended Audience :: Science/Research
Classifier: License :: OSI Approved :: MIT License
Classifier: Operating System :: OS Independent
Classifier: Programming Language :: Python
Classifier: Topic :: Scientific/Engineering :: GIS
